local_visualizer/__init__.py
local_visualizer/local_visualizer.py
local_visualizer-0.2.0.dist-info/DESCRIPTION.rst
local_visualizer-0.2.0.dist-info/METADATA
local_visualizer-0.2.0.dist-info/RECORD
local_visualizer-0.2.0.dist-info/WHEEL
local_visualizer-0.2.0.dist-info/metadata.json
local_visualizer-0.2.0.dist-info/top_level.txt
