Metadata-Version: 2.0
Name: local-visualizer
Version: 0.2.0
Summary: Simple python api to visualize the plots in a script.
Home-page: https://github.com/psvishnu91/local_visualizer
Author: Vishnu P Sreenivasan
Author-email: psvishnu.91@gmail.com
License: MIT license
Keywords: local_visualizer
Platform: UNKNOWN
Classifier: Development Status :: 2 - Pre-Alpha
Classifier: Intended Audience :: Developers
Classifier: License :: OSI Approved :: MIT License
Classifier: Natural Language :: English
Classifier: Programming Language :: Python :: 2.7
Requires-Dist: matplotlib
